analysis/__init__.py
analysis/plotHelper.py
analysis/plotting.py
utilities/__init__.py
utilities/chemistryUtilities.py
utilities/dataframeUtilities.py
utilities/dictUtilities.py
utilities/listUtilities.py
utilities/numerics.py
utilities/astroTools/__init__.py
utilities/astroTools/spectralUtilities.py
sadtools-0.0.2.dist-info/LICENSE.txt
sadtools-0.0.2.dist-info/METADATA
sadtools-0.0.2.dist-info/WHEEL
sadtools-0.0.2.dist-info/top_level.txt
sadtools-0.0.2.dist-info/RECORD
