Metadata-Version: 2.1
Name: sadtools
Version: 0.0.2
Summary: A collection of useful plotting, analysis and manipulation scripts for data science.
Home-page: https://github.com/SiddhantDeshmukh/usefulScripts
Author: Siddhant A. Deshmukh
Author-email: siddhant593@gmail.com
License: UNKNOWN
Platform: UNKNOWN
Classifier: Programming Language :: Python :: 3
Classifier: License :: OSI Approved :: MIT License
Classifier: Operating System :: OS Independent
Requires-Python: >=3.6
